exorigsim/__init__.py
exorigsim/dummy.exe
exorigsim/main.py
exorigsim/watchdog.vbs
exorigsim-0.1.0.dist-info/METADATA
exorigsim-0.1.0.dist-info/WHEEL
exorigsim-0.1.0.dist-info/top_level.txt
exorigsim-0.1.0.dist-info/RECORD
